figure_eight_client/__init__.py
figure_eight_client/figure_eight_client.py
tests/__init__.py
tests/test_figure_eight_client.py
figure_eight_client-1.1.0.dist-info/LICENSE
figure_eight_client-1.1.0.dist-info/METADATA
figure_eight_client-1.1.0.dist-info/WHEEL
figure_eight_client-1.1.0.dist-info/top_level.txt
figure_eight_client-1.1.0.dist-info/RECORD
