Metadata-Version: 2.1
Name: figure-eight-client
Version: 1.1.0
Summary: Simple client for the Figure Eight API
Home-page: https://github.com/de1ux/figure-eight-python-client
Author: Nathan Evans
Author-email: evans.nathan.j@gmail.com
License: UNKNOWN
Platform: UNKNOWN
Classifier: Programming Language :: Python
Classifier: License :: OSI Approved :: MIT License
Classifier: Operating System :: OS Independent
Requires-Dist: requests
